Metadata-Version: 1.1
Name: scopus
Version: 2.0.9
Summary: Outdated package
Home-page: https://scopus.readthedocs.io/en/stable/
Author: 'John Kitchin and Michael E. Rose
Author-email: Michael.Ernst.Rose@gmail.com
License: UNKNOWN
Platform: UNKNOWN
Classifier: Development Status :: 7 - Inactive
Classifier: Intended Audience :: Science/Research
Classifier: Natural Language :: English
Classifier: Operating System :: OS Independent
Classifier: Programming Language :: Python :: 2.7
Classifier: Programming Language :: Python :: 3.5
Classifier: Programming Language :: Python :: 3.6
Classifier: Programming Language :: Python :: 3.7
